<?xml version="1.0" encoding="utf-8"?>
<ArrayOfDependency xmlns:xsi="http://www.w3.org/2001/XMLSchema-instance" xmlns:xsd="http://www.w3.org/2001/XMLSchema">
  <Dependency>
    <Id>10000</Id>
    <DependentTask>1002</DependentTask>
    <DependsOnTask>1000</DependsOnTask>
  </Dependency>
  <Dependency>
    <Id>10001</Id>
    <DependentTask>1003</DependentTask>
    <DependsOnTask>1001</DependsOnTask>
  </Dependency>
  <Dependency>
    <Id>10002</Id>
    <DependentTask>1004</DependentTask>
    <DependsOnTask>1002</DependsOnTask>
  </Dependency>
  <Dependency>
    <Id>10003</Id>
    <DependentTask>1004</DependentTask>
    <DependsOnTask>1003</DependsOnTask>
  </Dependency>
  <Dependency>
    <Id>10004</Id>
    <DependentTask>1005</DependentTask>
    <DependsOnTask>1000</DependsOnTask>
  </Dependency>
  <Dependency>
    <Id>10005</Id>
    <DependentTask>1006</DependentTask>
    <DependsOnTask>1004</DependsOnTask>
  </Dependency>
  <Dependency>
    <Id>10006</Id>
    <DependentTask>1006</DependentTask>
    <DependsOnTask>1002</DependsOnTask>
  </Dependency>
  <Dependency>
    <Id>10007</Id>
    <DependentTask>1007</DependentTask>
    <DependsOnTask>1006</DependsOnTask>
  </Dependency>
  <Dependency>
    <Id>10008</Id>
    <DependentTask>1008</DependentTask>
    <DependsOnTask>1005</DependsOnTask>
  </Dependency>
  <Dependency>
    <Id>10009</Id>
    <DependentTask>1008</DependentTask>
    <DependsOnTask>1007</DependsOnTask>
  </Dependency>
  <Dependency>
    <Id>10010</Id>
    <DependentTask>1009</DependentTask>
    <DependsOnTask>1008</DependsOnTask>
  </Dependency>
  <Dependency>
    <Id>10011</Id>
    <DependentTask>1010</DependentTask>
    <DependsOnTask>1009</DependsOnTask>
  </Dependency>
  <Dependency>
    <Id>10012</Id>
    <DependentTask>1011</DependentTask>
    <DependsOnTask>1010</DependsOnTask>
  </Dependency>
  <Dependency>
    <Id>10013</Id>
    <DependentTask>1012</DependentTask>
    <DependsOnTask>1011</DependsOnTask>
  </Dependency>
  <Dependency>
    <Id>10014</Id>
    <DependentTask>1013</DependentTask>
    <DependsOnTask>1012</DependsOnTask>
  </Dependency>
  <Dependency>
    <Id>10015</Id>
    <DependentTask>1014</DependentTask>
    <DependsOnTask>1013</DependsOnTask>
  </Dependency>
  <Dependency>
    <Id>10016</Id>
    <DependentTask>1002</DependentTask>
    <DependsOnTask>1000</DependsOnTask>
  </Dependency>
  <Dependency>
    <Id>10017</Id>
    <DependentTask>1003</DependentTask>
    <DependsOnTask>1001</DependsOnTask>
  </Dependency>
  <Dependency>
    <Id>10018</Id>
    <DependentTask>1004</DependentTask>
    <DependsOnTask>1002</DependsOnTask>
  </Dependency>
  <Dependency>
    <Id>10019</Id>
    <DependentTask>1004</DependentTask>
    <DependsOnTask>1003</DependsOnTask>
  </Dependency>
  <Dependency>
    <Id>10020</Id>
    <DependentTask>1005</DependentTask>
    <DependsOnTask>1000</DependsOnTask>
  </Dependency>
  <Dependency>
    <Id>10021</Id>
    <DependentTask>1006</DependentTask>
    <DependsOnTask>1004</DependsOnTask>
  </Dependency>
  <Dependency>
    <Id>10022</Id>
    <DependentTask>1006</DependentTask>
    <DependsOnTask>1002</DependsOnTask>
  </Dependency>
  <Dependency>
    <Id>10023</Id>
    <DependentTask>1007</DependentTask>
    <DependsOnTask>1006</DependsOnTask>
  </Dependency>
  <Dependency>
    <Id>10024</Id>
    <DependentTask>1008</DependentTask>
    <DependsOnTask>1005</DependsOnTask>
  </Dependency>
  <Dependency>
    <Id>10025</Id>
    <DependentTask>1008</DependentTask>
    <DependsOnTask>1007</DependsOnTask>
  </Dependency>
  <Dependency>
    <Id>10026</Id>
    <DependentTask>1009</DependentTask>
    <DependsOnTask>1008</DependsOnTask>
  </Dependency>
  <Dependency>
    <Id>10027</Id>
    <DependentTask>1010</DependentTask>
    <DependsOnTask>1009</DependsOnTask>
  </Dependency>
  <Dependency>
    <Id>10028</Id>
    <DependentTask>1011</DependentTask>
    <DependsOnTask>1010</DependsOnTask>
  </Dependency>
  <Dependency>
    <Id>10029</Id>
    <DependentTask>1012</DependentTask>
    <DependsOnTask>1011</DependsOnTask>
  </Dependency>
  <Dependency>
    <Id>10030</Id>
    <DependentTask>1013</DependentTask>
    <DependsOnTask>1012</DependsOnTask>
  </Dependency>
  <Dependency>
    <Id>10031</Id>
    <DependentTask>1014</DependentTask>
    <DependsOnTask>1013</DependsOnTask>
  </Dependency>
  <Dependency>
    <Id>10032</Id>
    <DependentTask>1015</DependentTask>
    <DependsOnTask>1014</DependsOnTask>
  </Dependency>
  <Dependency>
    <Id>10033</Id>
    <DependentTask>1016</DependentTask>
    <DependsOnTask>1015</DependsOnTask>
  </Dependency>
  <Dependency>
    <Id>10034</Id>
    <DependentTask>1017</DependentTask>
    <DependsOnTask>1016</DependsOnTask>
  </Dependency>
  <Dependency>
    <Id>10035</Id>
    <DependentTask>1018</DependentTask>
    <DependsOnTask>1017</DependsOnTask>
  </Dependency>
  <Dependency>
    <Id>10036</Id>
    <DependentTask>1019</DependentTask>
    <DependsOnTask>1018</DependsOnTask>
  </Dependency>
  <Dependency>
    <Id>10037</Id>
    <DependentTask>1020</DependentTask>
    <DependsOnTask>1019</DependsOnTask>
  </Dependency>
  <Dependency>
    <Id>10038</Id>
    <DependentTask>1021</DependentTask>
    <DependsOnTask>1020</DependsOnTask>
  </Dependency>
  <Dependency>
    <Id>10039</Id>
    <DependentTask>1022</DependentTask>
    <DependsOnTask>1021</DependsOnTask>
  </Dependency>
  <Dependency>
    <Id>10040</Id>
    <DependentTask>1023</DependentTask>
    <DependsOnTask>1022</DependsOnTask>
  </Dependency>
  <Dependency>
    <Id>10041</Id>
    <DependentTask>1024</DependentTask>
    <DependsOnTask>1023</DependsOnTask>
  </Dependency>
  <Dependency>
    <Id>10042</Id>
    <DependentTask>1025</DependentTask>
    <DependsOnTask>1024</DependsOnTask>
  </Dependency>
  <Dependency>
    <Id>10043</Id>
    <DependentTask>1026</DependentTask>
    <DependsOnTask>1025</DependsOnTask>
  </Dependency>
  <Dependency>
    <Id>10044</Id>
    <DependentTask>1027</DependentTask>
    <DependsOnTask>1026</DependsOnTask>
  </Dependency>
  <Dependency>
    <Id>10045</Id>
    <DependentTask>1028</DependentTask>
    <DependsOnTask>1027</DependsOnTask>
  </Dependency>
  <Dependency>
    <Id>10046</Id>
    <DependentTask>1002</DependentTask>
    <DependsOnTask>1001</DependsOnTask>
  </Dependency>
  <Dependency>
    <Id>10047</Id>
    <DependentTask>1005</DependentTask>
    <DependsOnTask>1003</DependsOnTask>
  </Dependency>
  <Dependency>
    <Id>10048</Id>
    <DependentTask>1008</DependentTask>
    <DependsOnTask>1006</DependsOnTask>
  </Dependency>
  <Dependency>
    <Id>10049</Id>
    <DependentTask>1011</DependentTask>
    <DependsOnTask>1009</DependsOnTask>
  </Dependency>
  <Dependency>
    <Id>10050</Id>
    <DependentTask>1012</DependentTask>
    <DependsOnTask>1010</DependsOnTask>
  </Dependency>
  <Dependency>
    <Id>10051</Id>
    <DependentTask>1014</DependentTask>
    <DependsOnTask>1012</DependsOnTask>
  </Dependency>
  <Dependency>
    <Id>10052</Id>
    <DependentTask>1017</DependentTask>
    <DependsOnTask>1014</DependsOnTask>
  </Dependency>
  <Dependency>
    <Id>10053</Id>
    <DependentTask>1018</DependentTask>
    <DependsOnTask>1016</DependsOnTask>
  </Dependency>
  <Dependency>
    <Id>10054</Id>
    <DependentTask>1020</DependentTask>
    <DependsOnTask>1018</DependsOnTask>
  </Dependency>
  <Dependency>
    <Id>10055</Id>
    <DependentTask>1021</DependentTask>
    <DependsOnTask>1019</DependsOnTask>
  </Dependency>
  <Dependency>
    <Id>10056</Id>
    <DependentTask>1022</DependentTask>
    <DependsOnTask>1020</DependsOnTask>
  </Dependency>
  <Dependency>
    <Id>10057</Id>
    <DependentTask>1023</DependentTask>
    <DependsOnTask>1021</DependsOnTask>
  </Dependency>
  <Dependency>
    <Id>10058</Id>
    <DependentTask>1024</DependentTask>
    <DependsOnTask>1022</DependsOnTask>
  </Dependency>
  <Dependency>
    <Id>10059</Id>
    <DependentTask>1026</DependentTask>
    <DependsOnTask>1024</DependsOnTask>
  </Dependency>
  <Dependency>
    <Id>10060</Id>
    <DependentTask>1027</DependentTask>
    <DependsOnTask>1025</DependsOnTask>
  </Dependency>
  <Dependency>
    <Id>10061</Id>
    <DependentTask>1028</DependentTask>
    <DependsOnTask>1026</DependsOnTask>
  </Dependency>
  <Dependency>
    <Id>10062</Id>
    <DependentTask>1029</DependentTask>
    <DependsOnTask>1027</DependsOnTask>
  </Dependency>
  <Dependency>
    <Id>10063</Id>
    <DependentTask>1009</DependentTask>
    <DependsOnTask>1002</DependsOnTask>
  </Dependency>
  <Dependency>
    <Id>10064</Id>
    <DependentTask>1015</DependentTask>
    <DependsOnTask>1013</DependsOnTask>
  </Dependency>
  <Dependency>
    <Id>10065</Id>
    <DependentTask>1019</DependentTask>
    <DependsOnTask>1017</DependsOnTask>
  </Dependency>
  <Dependency>
    <Id>10066</Id>
    <DependentTask>1002</DependentTask>
    <DependsOnTask>1000</DependsOnTask>
  </Dependency>
  <Dependency>
    <Id>10067</Id>
    <DependentTask>1003</DependentTask>
    <DependsOnTask>1001</DependsOnTask>
  </Dependency>
  <Dependency>
    <Id>10068</Id>
    <DependentTask>1004</DependentTask>
    <DependsOnTask>1002</DependsOnTask>
  </Dependency>
  <Dependency>
    <Id>10069</Id>
    <DependentTask>1004</DependentTask>
    <DependsOnTask>1003</DependsOnTask>
  </Dependency>
  <Dependency>
    <Id>10070</Id>
    <DependentTask>1005</DependentTask>
    <DependsOnTask>1000</DependsOnTask>
  </Dependency>
  <Dependency>
    <Id>10071</Id>
    <DependentTask>1006</DependentTask>
    <DependsOnTask>1004</DependsOnTask>
  </Dependency>
  <Dependency>
    <Id>10072</Id>
    <DependentTask>1006</DependentTask>
    <DependsOnTask>1002</DependsOnTask>
  </Dependency>
  <Dependency>
    <Id>10073</Id>
    <DependentTask>1007</DependentTask>
    <DependsOnTask>1006</DependsOnTask>
  </Dependency>
  <Dependency>
    <Id>10074</Id>
    <DependentTask>1008</DependentTask>
    <DependsOnTask>1005</DependsOnTask>
  </Dependency>
  <Dependency>
    <Id>10075</Id>
    <DependentTask>1008</DependentTask>
    <DependsOnTask>1007</DependsOnTask>
  </Dependency>
  <Dependency>
    <Id>10076</Id>
    <DependentTask>1009</DependentTask>
    <DependsOnTask>1008</DependsOnTask>
  </Dependency>
  <Dependency>
    <Id>10077</Id>
    <DependentTask>1010</DependentTask>
    <DependsOnTask>1009</DependsOnTask>
  </Dependency>
  <Dependency>
    <Id>10078</Id>
    <DependentTask>1011</DependentTask>
    <DependsOnTask>1010</DependsOnTask>
  </Dependency>
  <Dependency>
    <Id>10079</Id>
    <DependentTask>1012</DependentTask>
    <DependsOnTask>1011</DependsOnTask>
  </Dependency>
  <Dependency>
    <Id>10080</Id>
    <DependentTask>1013</DependentTask>
    <DependsOnTask>1012</DependsOnTask>
  </Dependency>
  <Dependency>
    <Id>10081</Id>
    <DependentTask>1014</DependentTask>
    <DependsOnTask>1013</DependsOnTask>
  </Dependency>
  <Dependency>
    <Id>10082</Id>
    <DependentTask>1015</DependentTask>
    <DependsOnTask>1014</DependsOnTask>
  </Dependency>
  <Dependency>
    <Id>10083</Id>
    <DependentTask>1016</DependentTask>
    <DependsOnTask>1015</DependsOnTask>
  </Dependency>
  <Dependency>
    <Id>10084</Id>
    <DependentTask>1017</DependentTask>
    <DependsOnTask>1016</DependsOnTask>
  </Dependency>
  <Dependency>
    <Id>10085</Id>
    <DependentTask>1018</DependentTask>
    <DependsOnTask>1017</DependsOnTask>
  </Dependency>
  <Dependency>
    <Id>10086</Id>
    <DependentTask>1019</DependentTask>
    <DependsOnTask>1018</DependsOnTask>
  </Dependency>
  <Dependency>
    <Id>10087</Id>
    <DependentTask>1020</DependentTask>
    <DependsOnTask>1019</DependsOnTask>
  </Dependency>
  <Dependency>
    <Id>10088</Id>
    <DependentTask>1021</DependentTask>
    <DependsOnTask>1020</DependsOnTask>
  </Dependency>
  <Dependency>
    <Id>10089</Id>
    <DependentTask>1022</DependentTask>
    <DependsOnTask>1021</DependsOnTask>
  </Dependency>
  <Dependency>
    <Id>10090</Id>
    <DependentTask>1023</DependentTask>
    <DependsOnTask>1022</DependsOnTask>
  </Dependency>
  <Dependency>
    <Id>10091</Id>
    <DependentTask>1024</DependentTask>
    <DependsOnTask>1023</DependsOnTask>
  </Dependency>
  <Dependency>
    <Id>10092</Id>
    <DependentTask>1025</DependentTask>
    <DependsOnTask>1024</DependsOnTask>
  </Dependency>
  <Dependency>
    <Id>10093</Id>
    <DependentTask>1026</DependentTask>
    <DependsOnTask>1025</DependsOnTask>
  </Dependency>
  <Dependency>
    <Id>10094</Id>
    <DependentTask>1027</DependentTask>
    <DependsOnTask>1026</DependsOnTask>
  </Dependency>
  <Dependency>
    <Id>10095</Id>
    <DependentTask>1028</DependentTask>
    <DependsOnTask>1027</DependsOnTask>
  </Dependency>
  <Dependency>
    <Id>10096</Id>
    <DependentTask>1002</DependentTask>
    <DependsOnTask>1001</DependsOnTask>
  </Dependency>
  <Dependency>
    <Id>10097</Id>
    <DependentTask>1005</DependentTask>
    <DependsOnTask>1003</DependsOnTask>
  </Dependency>
  <Dependency>
    <Id>10098</Id>
    <DependentTask>1008</DependentTask>
    <DependsOnTask>1006</DependsOnTask>
  </Dependency>
  <Dependency>
    <Id>10099</Id>
    <DependentTask>1011</DependentTask>
    <DependsOnTask>1009</DependsOnTask>
  </Dependency>
  <Dependency>
    <Id>10100</Id>
    <DependentTask>1012</DependentTask>
    <DependsOnTask>1010</DependsOnTask>
  </Dependency>
  <Dependency>
    <Id>10101</Id>
    <DependentTask>1014</DependentTask>
    <DependsOnTask>1012</DependsOnTask>
  </Dependency>
  <Dependency>
    <Id>10102</Id>
    <DependentTask>1017</DependentTask>
    <DependsOnTask>1014</DependsOnTask>
  </Dependency>
  <Dependency>
    <Id>10103</Id>
    <DependentTask>1018</DependentTask>
    <DependsOnTask>1016</DependsOnTask>
  </Dependency>
  <Dependency>
    <Id>10104</Id>
    <DependentTask>1020</DependentTask>
    <DependsOnTask>1018</DependsOnTask>
  </Dependency>
  <Dependency>
    <Id>10105</Id>
    <DependentTask>1021</DependentTask>
    <DependsOnTask>1019</DependsOnTask>
  </Dependency>
  <Dependency>
    <Id>10106</Id>
    <DependentTask>1022</DependentTask>
    <DependsOnTask>1020</DependsOnTask>
  </Dependency>
  <Dependency>
    <Id>10107</Id>
    <DependentTask>1023</DependentTask>
    <DependsOnTask>1021</DependsOnTask>
  </Dependency>
  <Dependency>
    <Id>10108</Id>
    <DependentTask>1024</DependentTask>
    <DependsOnTask>1022</DependsOnTask>
  </Dependency>
  <Dependency>
    <Id>10109</Id>
    <DependentTask>1026</DependentTask>
    <DependsOnTask>1024</DependsOnTask>
  </Dependency>
  <Dependency>
    <Id>10110</Id>
    <DependentTask>1027</DependentTask>
    <DependsOnTask>1025</DependsOnTask>
  </Dependency>
  <Dependency>
    <Id>10111</Id>
    <DependentTask>1028</DependentTask>
    <DependsOnTask>1026</DependsOnTask>
  </Dependency>
  <Dependency>
    <Id>10112</Id>
    <DependentTask>1029</DependentTask>
    <DependsOnTask>1027</DependsOnTask>
  </Dependency>
  <Dependency>
    <Id>10113</Id>
    <DependentTask>1009</DependentTask>
    <DependsOnTask>1002</DependsOnTask>
  </Dependency>
  <Dependency>
    <Id>10114</Id>
    <DependentTask>1015</DependentTask>
    <DependsOnTask>1013</DependsOnTask>
  </Dependency>
  <Dependency>
    <Id>10115</Id>
    <DependentTask>1019</DependentTask>
    <DependsOnTask>1017</DependsOnTask>
  </Dependency>
  <dependencys>
    <Id>10116</Id>
    <DependentTask>1002</DependentTask>
    <DependentOnTask>1000</DependentOnTask>
  </dependencys>
  <dependencys>
    <Id>10117</Id>
    <DependentTask>1003</DependentTask>
    <DependentOnTask>1001</DependentOnTask>
  </dependencys>
  <dependencys>
    <Id>10118</Id>
    <DependentTask>1004</DependentTask>
    <DependentOnTask>1002</DependentOnTask>
  </dependencys>
  <dependencys>
    <Id>10119</Id>
    <DependentTask>1004</DependentTask>
    <DependentOnTask>1003</DependentOnTask>
  </dependencys>
  <dependencys>
    <Id>10120</Id>
    <DependentTask>1005</DependentTask>
    <DependentOnTask>1000</DependentOnTask>
  </dependencys>
  <dependencys>
    <Id>10121</Id>
    <DependentTask>1006</DependentTask>
    <DependentOnTask>1004</DependentOnTask>
  </dependencys>
  <dependencys>
    <Id>10122</Id>
    <DependentTask>1006</DependentTask>
    <DependentOnTask>1002</DependentOnTask>
  </dependencys>
  <dependencys>
    <Id>10123</Id>
    <DependentTask>1007</DependentTask>
    <DependentOnTask>1006</DependentOnTask>
  </dependencys>
  <dependencys>
    <Id>10124</Id>
    <DependentTask>1008</DependentTask>
    <DependentOnTask>1005</DependentOnTask>
  </dependencys>
  <dependencys>
    <Id>10125</Id>
    <DependentTask>1008</DependentTask>
    <DependentOnTask>1007</DependentOnTask>
  </dependencys>
  <dependencys>
    <Id>10126</Id>
    <DependentTask>1009</DependentTask>
    <DependentOnTask>1008</DependentOnTask>
  </dependencys>
  <dependencys>
    <Id>10127</Id>
    <DependentTask>1010</DependentTask>
    <DependentOnTask>1009</DependentOnTask>
  </dependencys>
  <dependencys>
    <Id>10128</Id>
    <DependentTask>1011</DependentTask>
    <DependentOnTask>1010</DependentOnTask>
  </dependencys>
  <dependencys>
    <Id>10129</Id>
    <DependentTask>1012</DependentTask>
    <DependentOnTask>1011</DependentOnTask>
  </dependencys>
  <dependencys>
    <Id>10130</Id>
    <DependentTask>1013</DependentTask>
    <DependentOnTask>1012</DependentOnTask>
  </dependencys>
  <dependencys>
    <Id>10131</Id>
    <DependentTask>1014</DependentTask>
    <DependentOnTask>1013</DependentOnTask>
  </dependencys>
  <dependencys>
    <Id>10132</Id>
    <DependentTask>1015</DependentTask>
    <DependentOnTask>1014</DependentOnTask>
  </dependencys>
  <dependencys>
    <Id>10133</Id>
    <DependentTask>1016</DependentTask>
    <DependentOnTask>1015</DependentOnTask>
  </dependencys>
  <dependencys>
    <Id>10134</Id>
    <DependentTask>1017</DependentTask>
    <DependentOnTask>1016</DependentOnTask>
  </dependencys>
  <dependencys>
    <Id>10135</Id>
    <DependentTask>1018</DependentTask>
    <DependentOnTask>1017</DependentOnTask>
  </dependencys>
  <dependencys>
    <Id>10136</Id>
    <DependentTask>1019</DependentTask>
    <DependentOnTask>1018</DependentOnTask>
  </dependencys>
  <dependencys>
    <Id>10137</Id>
    <DependentTask>1020</DependentTask>
    <DependentOnTask>1019</DependentOnTask>
  </dependencys>
  <dependencys>
    <Id>10138</Id>
    <DependentTask>1021</DependentTask>
    <DependentOnTask>1020</DependentOnTask>
  </dependencys>
  <dependencys>
    <Id>10140</Id>
    <DependentTask>1002</DependentTask>
    <DependentOnTask>1000</DependentOnTask>
  </dependencys>
  <dependencys>
    <Id>10141</Id>
    <DependentTask>1003</DependentTask>
    <DependentOnTask>1001</DependentOnTask>
  </dependencys>
  <dependencys>
    <Id>10142</Id>
    <DependentTask>1004</DependentTask>
    <DependentOnTask>1002</DependentOnTask>
  </dependencys>
  <dependencys>
    <Id>10143</Id>
    <DependentTask>1004</DependentTask>
    <DependentOnTask>1003</DependentOnTask>
  </dependencys>
  <dependencys>
    <Id>10144</Id>
    <DependentTask>1005</DependentTask>
    <DependentOnTask>1000</DependentOnTask>
  </dependencys>
  <dependencys>
    <Id>10145</Id>
    <DependentTask>1006</DependentTask>
    <DependentOnTask>1004</DependentOnTask>
  </dependencys>
  <dependencys>
    <Id>10146</Id>
    <DependentTask>1006</DependentTask>
    <DependentOnTask>1002</DependentOnTask>
  </dependencys>
  <dependencys>
    <Id>10147</Id>
    <DependentTask>1007</DependentTask>
    <DependentOnTask>1006</DependentOnTask>
  </dependencys>
  <dependencys>
    <Id>10148</Id>
    <DependentTask>1008</DependentTask>
    <DependentOnTask>1005</DependentOnTask>
  </dependencys>
  <dependencys>
    <Id>10149</Id>
    <DependentTask>1008</DependentTask>
    <DependentOnTask>1007</DependentOnTask>
  </dependencys>
  <dependencys>
    <Id>10150</Id>
    <DependentTask>1009</DependentTask>
    <DependentOnTask>1008</DependentOnTask>
  </dependencys>
  <dependencys>
    <Id>10151</Id>
    <DependentTask>1010</DependentTask>
    <DependentOnTask>1009</DependentOnTask>
  </dependencys>
  <dependencys>
    <Id>10152</Id>
    <DependentTask>1011</DependentTask>
    <DependentOnTask>1010</DependentOnTask>
  </dependencys>
  <dependencys>
    <Id>10153</Id>
    <DependentTask>1012</DependentTask>
    <DependentOnTask>1011</DependentOnTask>
  </dependencys>
  <dependencys>
    <Id>10154</Id>
    <DependentTask>1013</DependentTask>
    <DependentOnTask>1012</DependentOnTask>
  </dependencys>
  <dependencys>
    <Id>10155</Id>
    <DependentTask>1014</DependentTask>
    <DependentOnTask>1013</DependentOnTask>
  </dependencys>
  <dependencys>
    <Id>10156</Id>
    <DependentTask>1015</DependentTask>
    <DependentOnTask>1014</DependentOnTask>
  </dependencys>
  <dependencys>
    <Id>10157</Id>
    <DependentTask>1016</DependentTask>
    <DependentOnTask>1015</DependentOnTask>
  </dependencys>
  <dependencys>
    <Id>10158</Id>
    <DependentTask>1017</DependentTask>
    <DependentOnTask>1016</DependentOnTask>
  </dependencys>
  <dependencys>
    <Id>10159</Id>
    <DependentTask>1018</DependentTask>
    <DependentOnTask>1017</DependentOnTask>
  </dependencys>
  <dependencys>
    <Id>10160</Id>
    <DependentTask>1019</DependentTask>
    <DependentOnTask>1018</DependentOnTask>
  </dependencys>
  <dependencys>
    <Id>10161</Id>
    <DependentTask>1020</DependentTask>
    <DependentOnTask>1019</DependentOnTask>
  </dependencys>
  <dependencys>
    <Id>10162</Id>
    <DependentTask>1021</DependentTask>
    <DependentOnTask>1020</DependentOnTask>
  </dependencys>
  <dependencys>
    <Id>10163</Id>
    <DependentTask>1022</DependentTask>
    <DependentOnTask>1021</DependentOnTask>
  </dependencys>
  <dependencys>
    <Id>10164</Id>
    <DependentTask>1023</DependentTask>
    <DependentOnTask>1022</DependentOnTask>
  </dependencys>
  <dependencys>
    <Id>10165</Id>
    <DependentTask>1024</DependentTask>
    <DependentOnTask>1023</DependentOnTask>
  </dependencys>
  <dependencys>
    <Id>10166</Id>
    <DependentTask>1025</DependentTask>
    <DependentOnTask>1024</DependentOnTask>
  </dependencys>
  <dependencys>
    <Id>10167</Id>
    <DependentTask>1026</DependentTask>
    <DependentOnTask>1025</DependentOnTask>
  </dependencys>
  <dependencys>
    <Id>10168</Id>
    <DependentTask>1027</DependentTask>
    <DependentOnTask>1026</DependentOnTask>
  </dependencys>
  <dependencys>
    <Id>10169</Id>
    <DependentTask>1028</DependentTask>
    <DependentOnTask>1027</DependentOnTask>
  </dependencys>
  <dependencys>
    <Id>10170</Id>
    <DependentTask>1002</DependentTask>
    <DependentOnTask>1001</DependentOnTask>
  </dependencys>
  <dependencys>
    <Id>10171</Id>
    <DependentTask>1005</DependentTask>
    <DependentOnTask>1003</DependentOnTask>
  </dependencys>
  <dependencys>
    <Id>10172</Id>
    <DependentTask>1008</DependentTask>
    <DependentOnTask>1006</DependentOnTask>
  </dependencys>
  <dependencys>
    <Id>10173</Id>
    <DependentTask>1011</DependentTask>
    <DependentOnTask>1009</DependentOnTask>
  </dependencys>
  <dependencys>
    <Id>10174</Id>
    <DependentTask>1012</DependentTask>
    <DependentOnTask>1010</DependentOnTask>
  </dependencys>
  <dependencys>
    <Id>10175</Id>
    <DependentTask>1014</DependentTask>
    <DependentOnTask>1012</DependentOnTask>
  </dependencys>
  <dependencys>
    <Id>10176</Id>
    <DependentTask>1017</DependentTask>
    <DependentOnTask>1014</DependentOnTask>
  </dependencys>
  <dependencys>
    <Id>10177</Id>
    <DependentTask>1018</DependentTask>
    <DependentOnTask>1016</DependentOnTask>
  </dependencys>
  <dependencys>
    <Id>10178</Id>
    <DependentTask>1020</DependentTask>
    <DependentOnTask>1018</DependentOnTask>
  </dependencys>
  <dependencys>
    <Id>10179</Id>
    <DependentTask>1021</DependentTask>
    <DependentOnTask>1019</DependentOnTask>
  </dependencys>
  <dependencys>
    <Id>10180</Id>
    <DependentTask>1022</DependentTask>
    <DependentOnTask>1020</DependentOnTask>
  </dependencys>
  <dependencys>
    <Id>10181</Id>
    <DependentTask>1023</DependentTask>
    <DependentOnTask>1021</DependentOnTask>
  </dependencys>
  <dependencys>
    <Id>10182</Id>
    <DependentTask>1024</DependentTask>
    <DependentOnTask>1022</DependentOnTask>
  </dependencys>
  <dependencys>
    <Id>10183</Id>
    <DependentTask>1026</DependentTask>
    <DependentOnTask>1024</DependentOnTask>
  </dependencys>
  <dependencys>
    <Id>10184</Id>
    <DependentTask>1027</DependentTask>
    <DependentOnTask>1025</DependentOnTask>
  </dependencys>
  <dependencys>
    <Id>10185</Id>
    <DependentTask>1028</DependentTask>
    <DependentOnTask>1026</DependentOnTask>
  </dependencys>
  <dependencys>
    <Id>10186</Id>
    <DependentTask>1029</DependentTask>
    <DependentOnTask>1027</DependentOnTask>
  </dependencys>
  <dependencys>
    <Id>10187</Id>
    <DependentTask>1009</DependentTask>
    <DependentOnTask>1002</DependentOnTask>
  </dependencys>
  <dependencys>
    <Id>10188</Id>
    <DependentTask>1015</DependentTask>
    <DependentOnTask>1013</DependentOnTask>
  </dependencys>
  <dependencys>
    <Id>10189</Id>
    <DependentTask>1019</DependentTask>
    <DependentOnTask>1017</DependentOnTask>
  </dependencys>
</ArrayOfDependency>